Metadata-Version: 1.1
Name: pybashcomplete
Version: 0.0.4
Summary: Bash completion utility for python scripts
Home-page: https://www.bitbucket.org/johannestaas/pybashcomplete
Author: Johan Nestaas
Author-email: johannestaas@gmail.com
License: GPLv3+
Platform: UNKNOWN
Classifier: Development Status :: 3 - Alpha
Classifier: License :: OSI Approved :: GNU General Public License v3 or later (GPLv3+)
Classifier: Environment :: Console
Classifier: Environment :: X11 Applications :: Qt
Classifier: Environment :: MacOS X
Classifier: Operating System :: POSIX
Classifier: Operating System :: MacOS :: MacOS X
Classifier: Programming Language :: Python
